<?xml version="1.0" encoding="UTF-8"?>
<!-- Created with TexturePacker https://www.codeandweb.com/texturepacker -->
<!-- $TexturePacker:SmartUpdate:f6ded06002eda20ada200df14d92c425:26d76bbe975c8d25c2fd5a0154d98ded:8bbd6e684923a718c951c96e90710c0d$ -->
<!--Format:
n  => name of the sprite
x  => sprite x pos in texture
y  => sprite y pos in texture
w  => sprite width (may be trimmed)
h  => sprite height (may be trimmed)
pX => x pos of the pivot point (relative to sprite width)
pY => y pos of the pivot point (relative to sprite height)
oX => sprite's x-corner offset (only available if trimmed)
oY => sprite's y-corner offset (only available if trimmed)
oW => sprite's original width (only available if trimmed)
oH => sprite's original height (only available if trimmed)
r => 'y' only set if sprite is rotated
with polygon mode enabled:
vertices   => points in sprite coordinate system (x0,y0,x1,y1,x2,y2, ...)
verticesUV => points in sheet coordinate system (x0,y0,x1,y1,x2,y2, ...)
triangles  => sprite triangulation, 3 vertex indices per triangle
-->
<TextureAtlas imagePath="count bleck.png" width="1747" height="1413">
    <sprite n="idle_1.png" x="139" y="0" w="170" h="234" pX="0.5" pY="0.5"/>
    <sprite n="idle_2.png" x="309" y="0" w="170" h="234" pX="0.5" pY="0.5"/>
    <sprite n="idle_3.png" x="479" y="0" w="170" h="234" pX="0.5" pY="0.5"/>
    <sprite n="idle_4.png" x="822" y="0" w="170" h="234" pX="0.5" pY="0.5"/>
    <sprite n="idle_5.png" x="1021" y="234" w="171" h="234" pX="0.5" pY="0.5"/>
    <sprite n="idle_6.png" x="1532" y="234" w="171" h="234" pX="0.5" pY="0.5"/>
    <sprite n="idle_7.png" x="0" y="468" w="171" h="234" pX="0.5" pY="0.5"/>
    <sprite n="idle_8.png" x="171" y="468" w="172" h="234" pX="0.5" pY="0.5"/>
    <sprite n="idle_9.png" x="1575" y="703" w="172" h="235" pX="0.5" pY="0.5"/>
    <sprite n="idle_10.png" x="521" y="468" w="172" h="235" pX="0.5" pY="0.5"/>
    <sprite n="idle_11.png" x="693" y="468" w="173" h="235" pX="0.5" pY="0.5"/>
    <sprite n="idle_12.png" x="866" y="468" w="173" h="235" pX="0.5" pY="0.5"/>
    <sprite n="idle_13.png" x="1039" y="468" w="174" h="235" pX="0.5" pY="0.5"/>
    <sprite n="idle_14.png" x="1213" y="468" w="174" h="235" pX="0.5" pY="0.5"/>
    <sprite n="idle_15.png" x="1387" y="468" w="175" h="235" pX="0.5" pY="0.5"/>
    <sprite n="idle_16.png" x="1562" y="468" w="175" h="235" pX="0.5" pY="0.5"/>
    <sprite n="idle_17.png" x="0" y="703" w="176" h="235" pX="0.5" pY="0.5"/>
    <sprite n="idle_18.png" x="176" y="703" w="176" h="235" pX="0.5" pY="0.5"/>
    <sprite n="idle_19.png" x="352" y="703" w="176" h="235" pX="0.5" pY="0.5"/>
    <sprite n="idle_20.png" x="0" y="938" w="177" h="236" pX="0.5" pY="0.5"/>
    <sprite n="idle_21.png" x="177" y="938" w="177" h="236" pX="0.5" pY="0.5"/>
    <sprite n="idle_22.png" x="354" y="938" w="178" h="236" pX="0.5" pY="0.5"/>
    <sprite n="idle_23.png" x="532" y="938" w="178" h="236" pX="0.5" pY="0.5"/>
    <sprite n="idle_24.png" x="710" y="938" w="178" h="236" pX="0.5" pY="0.5"/>
    <sprite n="idle_25.png" x="888" y="938" w="178" h="236" pX="0.5" pY="0.5"/>
    <sprite n="idle_26.png" x="1066" y="938" w="178" h="236" pX="0.5" pY="0.5"/>
    <sprite n="idle_27.png" x="1244" y="938" w="178" h="236" pX="0.5" pY="0.5"/>
    <sprite n="idle_28.png" x="1422" y="938" w="177" h="236" pX="0.5" pY="0.5"/>
    <sprite n="idle_29.png" x="0" y="1174" w="177" h="236" pX="0.5" pY="0.5"/>
    <sprite n="idle_30.png" x="177" y="1174" w="177" h="236" pX="0.5" pY="0.5"/>
    <sprite n="idle_31.png" x="354" y="1174" w="176" h="236" pX="0.5" pY="0.5"/>
    <sprite n="idle_32.png" x="530" y="1174" w="176" h="236" pX="0.5" pY="0.5"/>
    <sprite n="idle_33.png" x="528" y="703" w="176" h="235" pX="0.5" pY="0.5"/>
    <sprite n="idle_34.png" x="704" y="703" w="175" h="235" pX="0.5" pY="0.5"/>
    <sprite n="idle_35.png" x="879" y="703" w="175" h="235" pX="0.5" pY="0.5"/>
    <sprite n="idle_36.png" x="1054" y="703" w="174" h="235" pX="0.5" pY="0.5"/>
    <sprite n="idle_37.png" x="1228" y="703" w="174" h="235" pX="0.5" pY="0.5"/>
    <sprite n="idle_38.png" x="1402" y="703" w="173" h="235" pX="0.5" pY="0.5"/>
    <sprite n="idle_39.png" x="649" y="0" w="173" h="234" pX="0.5" pY="0.5"/>
    <sprite n="idle_40.png" x="992" y="0" w="172" h="234" pX="0.5" pY="0.5"/>
    <sprite n="idle_41.png" x="1164" y="0" w="172" h="234" pX="0.5" pY="0.5"/>
    <sprite n="idle_42.png" x="1336" y="0" w="171" h="234" pX="0.5" pY="0.5"/>
    <sprite n="idle_43.png" x="1507" y="0" w="171" h="234" pX="0.5" pY="0.5"/>
    <sprite n="idle_44.png" x="0" y="234" w="171" h="234" pX="0.5" pY="0.5"/>
    <sprite n="idle_45.png" x="171" y="234" w="170" h="234" pX="0.5" pY="0.5"/>
    <sprite n="idle_46.png" x="341" y="234" w="170" h="234" pX="0.5" pY="0.5"/>
    <sprite n="idle_47.png" x="511" y="234" w="170" h="234" pX="0.5" pY="0.5"/>
    <sprite n="idle_48.png" x="681" y="234" w="170" h="234" pX="0.5" pY="0.5"/>
    <sprite n="idle_49.png" x="851" y="234" w="170" h="234" pX="0.5" pY="0.5"/>
    <sprite n="idle_50.png" x="1192" y="234" w="170" h="234" pX="0.5" pY="0.5"/>
    <sprite n="idle_51.png" x="1362" y="234" w="170" h="234" pX="0.5" pY="0.5"/>
    <sprite n="shadow.png" x="0" y="0" w="139" h="24" pX="0.5" pY="0.5"/>
    <sprite n="talking_1.png" x="343" y="468" w="178" h="234" pX="0.5" pY="0.5"/>
    <sprite n="talking_2.png" x="706" y="1174" w="178" h="236" pX="0.5" pY="0.5"/>
    <sprite n="talking_3.png" x="1062" y="1174" w="178" h="237" pX="0.5" pY="0.5"/>
    <sprite n="talking_4.png" x="1418" y="1174" w="178" h="239" pX="0.5" pY="0.5"/>
    <sprite n="talking_5.png" x="1240" y="1174" w="178" h="237" pX="0.5" pY="0.5"/>
    <sprite n="talking_6.png" x="884" y="1174" w="178" h="236" pX="0.5" pY="0.5"/>
</TextureAtlas>
